{"scopeName":"source.wren.tic80","name":"Wren TIC-80","fileTypes":["wren"],"injections":{"L:source.moon":{"patterns":[{"include":"#api"}]}},"patterns":[{"name":"support.class.library.wren.tic80","match":"\\bTIC\\b"},{"include":"#other"},{"include":"source.wren"}],"repository":{"api":{"patterns":[]},"other":{"patterns":[{"name":"entity.name.tag.wren.tic80.metadata","match":"^//\\s+(title|author|desc|script|input|saveid):\\s+(.+)$","captures":{"2":{"name":"string.unquoted.tic80.metadata.data"}}}]}}}